datetime_popover/__init__.py
datetime_popover/datetime_popover.glade
datetime_popover/datetime_popover.py
datetime_popover/tests/__init__.py
datetime_popover/tests/manual_test.py
datetime_popover/tests/test_dateTimePopover.py
gtk_datetime_popover-6.0.0.dist-info/WHEEL
gtk_datetime_popover-6.0.0.dist-info/METADATA
gtk_datetime_popover-6.0.0.dist-info/RECORD
